gitlab_mr_mcp/__init__.py
gitlab_mr_mcp/__main__.py
gitlab_mr_mcp/config.py
gitlab_mr_mcp/gitlab_api.py
gitlab_mr_mcp/logging_config.py
gitlab_mr_mcp/server.py
gitlab_mr_mcp/utils.py
gitlab_mr_mcp/tools/__init__.py
gitlab_mr_mcp/tools/create_merge_request.py
gitlab_mr_mcp/tools/get_branch_merge_requests.py
gitlab_mr_mcp/tools/get_commit_discussions.py
gitlab_mr_mcp/tools/get_job_log.py
gitlab_mr_mcp/tools/get_merge_request_details.py
gitlab_mr_mcp/tools/get_merge_request_pipeline.py
gitlab_mr_mcp/tools/get_merge_request_reviews.py
gitlab_mr_mcp/tools/get_merge_request_test_report.py
gitlab_mr_mcp/tools/get_pipeline_test_summary.py
gitlab_mr_mcp/tools/list_merge_requests.py
gitlab_mr_mcp/tools/list_project_labels.py
gitlab_mr_mcp/tools/list_project_members.py
gitlab_mr_mcp/tools/reply_to_review_comment.py
gitlab_mr_mcp/tools/update_merge_request.py
gitlab_mr_mcp-1.0.0.dist-info/METADATA
gitlab_mr_mcp-1.0.0.dist-info/WHEEL
gitlab_mr_mcp-1.0.0.dist-info/entry_points.txt
gitlab_mr_mcp-1.0.0.dist-info/licenses/LICENSE
gitlab_mr_mcp-1.0.0.dist-info/RECORD
