Metadata-Version: 2.4
Name: gitlab-mr-mcp
Version: 1.0.0
Summary: Connect your AI assistant to GitLab via MCP
Project-URL: Homepage, https://github.com/amirsina-mandegari/gitlab-mr-mcp
Project-URL: Repository, https://github.com/amirsina-mandegari/gitlab-mr-mcp
Project-URL: Documentation, https://github.com/amirsina-mandegari/gitlab-mr-mcp#readme
Project-URL: Issues, https://github.com/amirsina-mandegari/gitlab-mr-mcp/issues
Author-email: Amirsina Mandegari <mandegari.amirsina@gmail.com>
License: MIT License
License-File: LICENSE
Keywords: ai,assistant,gitlab,mcp,merge-request,model-context-protocol
Classifier: Development Status :: 4 - Beta
Classifier: Intended Audience :: Developers
Classifier: License :: OSI Approved :: MIT License
Classifier: Programming Language :: Python :: 3
Classifier: Programming Language :: Python :: 3.10
Classifier: Programming Language :: Python :: 3.11
Classifier: Programming Language :: Python :: 3.12
Classifier: Programming Language :: Python :: 3.13
Classifier: Programming Language :: Python :: 3.14
Requires-Python: >=3.10
Requires-Dist: aiohttp>=3.9.0
Requires-Dist: mcp>=1.0.0
Requires-Dist: pydantic-settings>=2.0.0
Requires-Dist: pydantic>=2.0.0
Requires-Dist: python-decouple>=3.8
Provides-Extra: dev
Requires-Dist: bandit>=1.7.7; extra == 'dev'
Requires-Dist: black>=24.0.0; extra == 'dev'
Requires-Dist: flake8-bugbear>=24.0.0; extra == 'dev'
Requires-Dist: flake8-print>=5.0.0; extra == 'dev'
Requires-Dist: flake8>=7.0.0; extra == 'dev'
Requires-Dist: isort>=5.13.0; extra == 'dev'
Requires-Dist: pre-commit>=3.6.0; extra == 'dev'
Requires-Dist: pytest-asyncio>=0.23.0; extra == 'dev'
Requires-Dist: pytest-mock>=3.12.0; extra == 'dev'
Requires-Dist: pytest>=8.0.0; extra == 'dev'
